HISTORY.rst
LICENSE
MANIFEST.in
README.rst
requirements.txt
setup.cfg
setup.py
visibudget/__init__.py
visibudget/__main__.py
visibudget/__version__.py
visibudget/help.py
visibudget.egg-info/PKG-INFO
visibudget.egg-info/SOURCES.txt
visibudget.egg-info/dependency_links.txt
visibudget.egg-info/not-zip-safe
visibudget.egg-info/requires.txt
visibudget.egg-info/top_level.txt
visibudget/cli/__init__.py